bom/__init__.py
bom-0.1.dev1.dist-info/LICENSE
bom-0.1.dev1.dist-info/METADATA
bom-0.1.dev1.dist-info/WHEEL
bom-0.1.dev1.dist-info/top_level.txt
bom-0.1.dev1.dist-info/RECORD
